std_hash/__init__.py
std_hash-0.1.2.dist-info/WHEEL
std_hash-0.1.2.dist-info/METADATA
std_hash-0.1.2.dist-info/RECORD
